edify/__init__.py
edify/builder/builder.py
edify/builder/errors.py
edify/builder/helpers/core.py
edify/builder/helpers/quantifiers.py
edify/builder/helpers/regex_vars.py
edify/builder/helpers/t.py
edify/library/__init__.py
edify/library/date.py
edify/library/guid.py
edify/library/ip.py
edify/library/mac.py
edify/library/mail.py
edify/library/password.py
edify/library/phone.py
edify/library/ssn.py
edify/library/url.py
edify/library/uuid.py
edify/library/zip.py
edify/library/support/zip.py
edify-0.2.2.dist-info/AUTHORS.rst
edify-0.2.2.dist-info/LICENSE
edify-0.2.2.dist-info/METADATA
edify-0.2.2.dist-info/WHEEL
edify-0.2.2.dist-info/top_level.txt
edify-0.2.2.dist-info/RECORD
